aether_support/__init__.py
aether_support/client.py
aether_support/exceptions.py
aether_support/py.typed
aether_support/types.py
aether_support/webhooks.py
aether_support-1.0.0.dist-info/licenses/LICENSE
aether_support-1.0.0.dist-info/METADATA
aether_support-1.0.0.dist-info/WHEEL
aether_support-1.0.0.dist-info/top_level.txt
aether_support-1.0.0.dist-info/RECORD
